json_schema_reducer.py
json_schema_reducer-0.1.4.dist-info/DESCRIPTION.rst
json_schema_reducer-0.1.4.dist-info/METADATA
json_schema_reducer-0.1.4.dist-info/RECORD
json_schema_reducer-0.1.4.dist-info/WHEEL
json_schema_reducer-0.1.4.dist-info/metadata.json
json_schema_reducer-0.1.4.dist-info/top_level.txt
