Metadata-Version: 2.0
Name: json-schema-reducer
Version: 0.1.4
Summary: Extract from a JSON/dict only whats in the JSON Schema
Home-page: https://github.com/peterbe/json-schema-reducer
Author: Peter Bengtsson
Author-email: mail@peterbe.com
License: MIT
Platform: UNKNOWN
Classifier: Intended Audience :: Developers
Classifier: License :: OSI Approved :: MIT License
Classifier: Programming Language :: Python :: 2
Classifier: Programming Language :: Python :: 3
